yuklovchi.py
yuklovchi-0.0.1.dist-info/WHEEL
yuklovchi-0.0.1.dist-info/METADATA
yuklovchi-0.0.1.dist-info/RECORD
