Metadata-Version: 2.1
Name: yuklovchi
Version: 0.0.1
Summary: Bu kutobxona yordamida YouTubedan va Instagramdan yuklashingiz mumkin.
Author: Nodir Bahodirov
Requires-Python: >=3.8,<4.0
Classifier: Programming Language :: Python :: 3
Classifier: Programming Language :: Python :: 3.8
Classifier: Programming Language :: Python :: 3.9
Classifier: Programming Language :: Python :: 3.10
Requires-Dist: instaloader (>=4.9.5,<5.0.0)
Requires-Dist: pytube (>=12.1.0,<13.0.0)
Requires-Dist: pywebio (>=1.6.3,<2.0.0)
